LICENCE
README.md
X引入留存(月).csv
setup.py
temp.xlsx
test.py
x引入留存11月(含删文).csv
x引入留存11月.csv
发文量.csv
引入作者.xlsx
留存数据情况.ipynb
dist/retention_model-0.0.1.tar.gz
retention_model/__init__.py
retention_model/x_retention_model.py
retention_model.egg-info/PKG-INFO
retention_model.egg-info/SOURCES.txt
retention_model.egg-info/dependency_links.txt
retention_model.egg-info/requires.txt
retention_model.egg-info/top_level.txt
retention_model/__pycache__/__init__.cpython-38.pyc
retention_model/__pycache__/x_retention_model.cpython-38.pyc