Metadata-Version: 2.1
Name: retention-model
Version: 0.0.2
Summary: package for predicting pubnum of X or others
Author: wufeipku
Author-email: wufei.pku@163.com
Classifier: Programming Language :: Python :: 3
Classifier: License :: OSI Approved :: MIT License
Classifier: Operating System :: OS Independent
License-File: LICENCE
